hyperband_snakemake/__init__.py
hyperband_snakemake/__main__.py
hyperband_snakemake/generator.py
hyperband_snakemake/search.py
hyperband_snakemake/writer.py
hyperband_snakemake/templates/Snakefile
hyperband_snakemake/templates/__init__.py
hyperband_snakemake/templates/config
hyperband_snakemake/templates/run.sh
hyperband_snakemake-0.0.1.dist-info/LICENSE
hyperband_snakemake-0.0.1.dist-info/METADATA
hyperband_snakemake-0.0.1.dist-info/WHEEL
hyperband_snakemake-0.0.1.dist-info/top_level.txt
hyperband_snakemake-0.0.1.dist-info/RECORD
