Metadata-Version: 2.1
Name: hyperband-snakemake
Version: 0.0.1
Summary: Orchestrate hyper-parameters search with snakemake
Home-page: https://github.com/e-dorigatti/hyperband-snakemake/
Author: e-dorigatti
Author-email: emilio.dorigatti@gmail.com
License: UNKNOWN
Platform: UNKNOWN
Classifier: Programming Language :: Python :: 3
Classifier: License :: OSI Approved :: GNU General Public License v3 (GPLv3)
Classifier: Operating System :: OS Independent
Requires-Python: >=3.6
Requires-Dist: click (>=7.1.2)
Requires-Dist: jinja2 (>=2.11.2)
